awssert/__init__.py
awssert/core.py
awssert/dynamodb.py
awssert/exceptions.py
awssert/hooks.py
awssert/iam.py
awssert/prefixes.py
awssert/s3.py
awssert/sns.py
test/__init__.py
test/conftest.py
test/test_core.py
test/test_dynamodb.py
test/test_iam.py
test/test_prefixes.py
test/test_s3.py
test/test_sns.py
awssert-1.0.0.dist-info/LICENSE
awssert-1.0.0.dist-info/METADATA
awssert-1.0.0.dist-info/WHEEL
awssert-1.0.0.dist-info/entry_points.txt
awssert-1.0.0.dist-info/top_level.txt
awssert-1.0.0.dist-info/RECORD
