Metadata-Version: 2.1
Name: awssert
Version: 1.0.0
Summary: Declarative assertions for AWS
Home-page: https://github.com/TSNoble/awssert
Author: Tom Noble
Author-email: t.s.noble@outlook.com
License: UNKNOWN
Project-URL: Bug Reports, https://github.com/TSNobleSoftware/awssert/issues
Project-URL: Source, https://github.com/TSNobleSoftware/awssert
Keywords: aws,python,pytest,boto3,testing
Platform: UNKNOWN
Classifier: Development Status :: 4 - Beta
Classifier: Intended Audience :: Developers
Classifier: License :: OSI Approved :: Apache Software License
Classifier: Framework :: AWS CDK
Classifier: Framework :: Pytest
Classifier: Programming Language :: Python :: 3
Classifier: Programming Language :: Python :: 3.6
Classifier: Programming Language :: Python :: 3.7
Classifier: Programming Language :: Python :: 3.8
Requires-Python: >=3.6
Requires-Dist: pytest (<=6.2.3)
Requires-Dist: boto3 (<=1.17.49)
Requires-Dist: mock (<=4.0.3)
Requires-Dist: python-dateutil (<=2.8.1)
Requires-Dist: docker (<=4.4.2)
